 [{
         "GlobalLocationNumber": "6241000010000",
         "BPName": "شركة الريحان للصناعات الغذائية"
     },
     {
         "GlobalLocationNumber": "6241000020009",
         "BPName": "شركة الواحة للصناعات الغذائية"
     },
     {
         "GlobalLocationNumber": "6241000030008",
         "BPName": "شركة الطيبات للصناعات الغذائية"
     },
     {
         "GlobalLocationNumber": "6240000004002",
         "BPName": "شركة الشافية الليبية للصناعات الغذائية"
     },
     {
         "GlobalLocationNumber": "6241000040007",
         "BPName": "شركة النسيم للصناعات الغذائية"
     },
     {
         "GlobalLocationNumber": "6240000005009",
         "BPName": "مصنع اصيلة لصناعة الحلويات 1"
     },
     {
         "GlobalLocationNumber": "6241000050006",
         "BPName": "شركة افريقيا لتعبئة المشروبات"
     },
     {
         "GlobalLocationNumber": "6241000520004",
         "BPName": "مطحن الزيتونة"
     },
     {
         "GlobalLocationNumber": "6240000525002",
         "BPName": "شركة الشهد لصناعة المواد الغذائية"
     },
     {
         "GlobalLocationNumber": "6240000010003",
         "BPName": "شركة الزيوت النباتية المساهمة"
     },
     {
         "GlobalLocationNumber": "6241003520001",
         "BPName": "شركة فراتا المساهمة 2"
     },
     {
         "GlobalLocationNumber": "6241000080003",
         "BPName": "شركة جودي للصناعات الغذائية"
     },
     {
         "GlobalLocationNumber": "6240000011000",
         "BPName": "شركة جنوب المتوسط  للتنمية الأهلية"
     },
     {
         "GlobalLocationNumber": "6240000012007",
         "BPName": "مصنع دلتا للصناعات البلاستكية"
     },
     {
         "GlobalLocationNumber": "6241000100008",
         "BPName": "تشاركية أبناء الفاندي"
     },
     {
         "GlobalLocationNumber": "6240000017002",
         "BPName": "شركة النبع للانتاج والخدمات التموينية المساهمة"
     },
     {
         "GlobalLocationNumber": "6240000018009",
         "BPName": "تشاركية الصافية لتعبئة المياه"
     },
     {
         "GlobalLocationNumber": "6240000020002",
         "BPName": "تشاركية القلعة لصناعة الصابون ومواد النظيف"
     },
     {
         "GlobalLocationNumber": "6240000024000",
         "BPName": "تشاركية شمال افريقيا لصناعة الصابون والمنظفات"
     },
     {
         "GlobalLocationNumber": "6240000026004",
         "BPName": "شركة الزهراء لصناعة المواد الغذائية"
     },
     {
         "GlobalLocationNumber": "6240000027001",
         "BPName": "تشاركية البردي لصناعة الورق الناعم"
     },
     {
         "GlobalLocationNumber": "6241000130005",
         "BPName": "تشاركية ارحومة للصناعات البلاستيكية"
     },
     {
         "GlobalLocationNumber": "6240000036003",
         "BPName": "مطحن عصام لتحميص وطحن البن"
     },
     {
         "GlobalLocationNumber": "6240000038007",
         "BPName": "شركة اولين هولدينغز المحدودة"
     },
     {
         "GlobalLocationNumber": "6240000041007",
         "BPName": "الشركة الوطنية للمطاحن والأعلاف المساهمة"
     },
     {
         "GlobalLocationNumber": "6240000044008",
         "BPName": "شركة أبو عطني لصناعة المشروبات"
     },
     {
         "GlobalLocationNumber": "6241000140004",
         "BPName": "شركة المعالي المساهمة لإستيراد مواد غذائية"
     },
     {
         "GlobalLocationNumber": "6240000046002",
         "BPName": "عقوب للبن و التوابل و المكسرات"
     },
     {
         "GlobalLocationNumber": "6240000049003",
         "BPName": "مصنع الأميرة للصناعات الغذائية"
     },
     {
         "GlobalLocationNumber": "6240000050009",
         "BPName": "تشاركية البريق لصناعة الصابون ومواد التنظيف"
     },
     {
         "GlobalLocationNumber": "6240000052003",
         "BPName": "شركة السهام الذهبية لصناعة الخبز والخبيز"
     },
     {
         "GlobalLocationNumber": "6241000170001",
         "BPName": "شركة التنارة للصيد وتعليب الاسماك"
     },
     {
         "GlobalLocationNumber": "6240000055004",
         "BPName": "مطحن رتاج"
     },
     {
         "GlobalLocationNumber": "6240000056001",
         "BPName": "مصنع علي سالم الارباح"
     },
     {
         "GlobalLocationNumber": "6240000064006",
         "BPName": "شركة زاد الخير"
     },
     {
         "GlobalLocationNumber": "6241000180000",
         "BPName": "شركة الطبيعة للصناعات الغذائية : ذات المسؤولية المحدودة"
     },
     {
         "GlobalLocationNumber": "6241000190009",
         "BPName": "شركة السنبلة لصناعات الغذائية"
     },
     {
         "GlobalLocationNumber": "6240000071004",
         "BPName": "تشاركية الساقي لتعبئة المياه"
     },
     {
         "GlobalLocationNumber": "6240000072001",
         "BPName": "مطحن اليُمن للبن والمكسرات"
     },
     {
         "GlobalLocationNumber": "6240000073008",
         "BPName": "شركة نسيم البحر مصراتة"
     },
     {
         "GlobalLocationNumber": "6240000075002",
         "BPName": "مخبز برقو"
     },
     {
         "GlobalLocationNumber": "6241002970005",
         "BPName": "شركة بيتنا لاستيراد المواد الغذائية والمواشي واللحوم"
     },
     {
         "GlobalLocationNumber": "6240000688004",
         "BPName": "شركة الغدير الصافي للصناعات الغذائية"
     },
     {
         "GlobalLocationNumber": "6240000689001",
         "BPName": "شركة الفصول الاربعة للصناعات الغذائية"
     },
     {
         "GlobalLocationNumber": "6241002980004",
         "BPName": "شركة دينار لاستيراد المواد الغذائية"
     },
     {
         "GlobalLocationNumber": "6241002990003",
         "BPName": "شركة عيون الغرب للصناعات الغذائية"
     },
     {
         "GlobalLocationNumber": "6241003000008",
         "BPName": "شركة منبع بلادي لتنقية وتعبئة المياه المعدنية والمشروبات الغازية والعصائر"
     },
     {
         "GlobalLocationNumber": "6241003010007",
         "BPName": "شركة العلامة الدولية لاستيراد المواشي واللحوم"
     },
     {
         "GlobalLocationNumber": "6241003020006",
         "BPName": "شركة المنتج العريق للصناعات الغدائية"
     },
     {
         "GlobalLocationNumber": "6241003030005",
         "BPName": "مصنع أجياد لتعبئة المياه"
     },
     {
         "GlobalLocationNumber": "6241003040004",
         "BPName": "مصنع الريان لصناعة الخبيز والنواشف"
     },
     {
         "GlobalLocationNumber": "6241003050003",
         "BPName": "شركة الحكيم لتعئة وتغليف الأعشاب الطبيعية"
     },
     {
         "GlobalLocationNumber": "6241003060002",
         "BPName": "مصنع الشروق لصناعة وتعبئة مياه الشرب"
     },
     {
         "GlobalLocationNumber": "6241003070001",
         "BPName": "شركة سكر العائلة لتعبئة وتغليف المواد الغذائية"
     },
     {
         "GlobalLocationNumber": "6241003080000",
         "BPName": "مراعي جنزور الأولى للصناعات الغذائية والألبان ومشتقاتها"
     },
     {
         "GlobalLocationNumber": "6241003090009",
         "BPName": "شركة اللؤلؤة الفريدة لاستيراد المواد الغذائية"
     },
     {
         "GlobalLocationNumber": "6241003100005",
         "BPName": "شركة خيرات الباشا لتعبئة وتغليف المواد الغذائية"
     },
     {
         "GlobalLocationNumber": "6241003110004",
         "BPName": "شركة سيليا للصناعات الغدائية"
     },
     {
         "GlobalLocationNumber": "6241003120003",
         "BPName": "شركة الفسيلة الخضراء للأستثمار والتنمية الزراعية"
     },
     {
         "GlobalLocationNumber": "6241003130002",
         "BPName": "شركة الأوسمة الجديدة ذ.م.م"
     },
     {
         "GlobalLocationNumber": "6241003140001",
         "BPName": "شركة إيكو لصناعة مواد التنظيف والكوزمات"
     },
     {
         "GlobalLocationNumber": "6241003150000",
         "BPName": "شركة الطاهي الدولي المحدودة للصناعات الغذائية والتموين"
     },
     {
         "GlobalLocationNumber": "6241003160009",
         "BPName": "مصنع الرواد لتعبئة العصائر ومياه الغازية ومعدنية"
     },
     {
         "GlobalLocationNumber": "6241003170008",
         "BPName": "شركة بيروت لصناعة الحلويات والخبيز"
     },
     {
         "GlobalLocationNumber": "6241003180007",
         "BPName": "مطحن شلوف للبن والتوابل"
     },
     {
         "GlobalLocationNumber": "6241003190006",
         "BPName": "شركة منارة الساحل لاستيراد المواد الغذائية"
     },
     {
         "GlobalLocationNumber": "6241003200002",
         "BPName": "شركة أصيل  لصناعة حفاظات الأطفال والمناديل الورقية"
     },
     {
         "GlobalLocationNumber": "6241003210001",
         "BPName": "شركة العين توزر لتعبئة المياه"
     },
     {
         "GlobalLocationNumber": "6241003220000",
         "BPName": "شركة مأمون الدولية لاستيراد المواد الغدائية"
     },
     {
         "GlobalLocationNumber": "6241003230009",
         "BPName": "شركة العيون العذبة لتعبئة المياه"
     },
     {
         "GlobalLocationNumber": "6241003240008",
         "BPName": "شركة ابراج التجارية لاستيراد المواد الغذائية"
     },
     {
         "GlobalLocationNumber": "6240000082000",
         "BPName": "تشاركية السراج لتعبئة المياه والمشروبات"
     },
     {
         "GlobalLocationNumber": "6240000690007",
         "BPName": "مجموعة الارتقاء لإستيراد المواد الغذائية والمواشي واللحوم"
     },
     {
         "GlobalLocationNumber": "6241003250007",
         "BPName": "شركة اطياف الخير لتعبئة المياه والمشروبات"
     },
     {
         "GlobalLocationNumber": "6241003260006",
         "BPName": "شركة البستان لتعبئة الارز و سكر ذات المسؤولية المحدودة"
     },
     {
         "GlobalLocationNumber": "6241003270005",
         "BPName": "شركة ايادي الرواد لتعبئة و تغليف المنظفات"
     },
     {
         "GlobalLocationNumber": "6241003280004",
         "BPName": "شركة نوفا النقية لتعبئة المياة والمشروبات ذ.م.م"
     },
     {
         "GlobalLocationNumber": "6241003290003",
         "BPName": "شركة بريفو لإستيراد المواد الغذائية والمواشي واللحوم"
     },
     {
         "GlobalLocationNumber": "6241003300009",
         "BPName": "شركة أطايب الزاد للصناعات الغذائية"
     },
     {
         "GlobalLocationNumber": "6241003310008",
         "BPName": "شركة السهل المتحد لعصر الزيتون"
     },
     {
         "GlobalLocationNumber": "6241003320007",
         "BPName": "شركة عرار وشركائه لإستيراد المواد الغذائية ذات توصية بسيطة"
     },
     {
         "GlobalLocationNumber": "6241003330006",
         "BPName": "شركة هافانا لبيع وتوزيع العصائر وخدمات المقاهي"
     },
     {
         "GlobalLocationNumber": "6241003350004",
         "BPName": "شركة السنبلة الوطنية للصناعات الغذائية"
     },
     {
         "GlobalLocationNumber": "6241003360003",
         "BPName": "مصنع المذاق لتعبئة وتنقية مياه الشرب"
     },
     {
         "GlobalLocationNumber": "6241003370002",
         "BPName": "شركة الأخوة الثمانية لتعبئة وتغليف المواد الغذائية بجميع أنواعها المحدودة"
     },
     {
         "GlobalLocationNumber": "6241003380001",
         "BPName": "شركة النبع النقي لتنقية وتحلية وتعبئة المياه وصناعة العصائر"
     },
     {
         "GlobalLocationNumber": "6241003390000",
         "BPName": "شركة البحر الأبيض المتوسط للصناعات الغذائية"
     },
     {
         "GlobalLocationNumber": "6241003400006",
         "BPName": "شركة اليرموك لإستيراد المواد الغذائية"
     },
     {
         "GlobalLocationNumber": "6241003410005",
         "BPName": "محل عمران محمد المؤنث"
     },
     {
         "GlobalLocationNumber": "6241003420004",
         "BPName": "شركة الريان القابضة المساهمة"
     },
     {
         "GlobalLocationNumber": "6241003430003",
         "BPName": "شركة الصلصة البيضاء لصناعات الغذائية ذ.م.م"
     },
     {
         "GlobalLocationNumber": "6241003440002",
         "BPName": "مصنع الاصيلة لصناعة الهريسة وتغليف السكر والبقوليات"
     },
     {
         "GlobalLocationNumber": "6241003450001",
         "BPName": "شركة الياقوت الاستيراد المواد الغذائية"
     },
     {
         "GlobalLocationNumber": "6241003460000",
         "BPName": "مصنع مصراتة لصناعة الانابيب البلاستيكية"
     },
     {
         "GlobalLocationNumber": "6241003470009",
         "BPName": "شركة الطائر الابيض للصناعات الغذائية"
     },
     {
         "GlobalLocationNumber": "6241003480008",
         "BPName": "شركة اجيال للصناعات الغذائية"
     },
     {
         "GlobalLocationNumber": "6241003490007",
         "BPName": "شركة الزين لصناعة المواد الغذائية والمشروبات"
     },
     {
         "GlobalLocationNumber": "6241003500003",
         "BPName": "شركة شمس الغداء لصناعة الخبز والحلويات"
     },
     {
         "GlobalLocationNumber": "6241003510002",
         "BPName": "شركة مزارع الفلاح لذبح الدواجن"
     },
     {
         "GlobalLocationNumber": "6241003530000",
         "BPName": "شركة الاندلس لصناعة الاعلاف"
     },
     {
         "GlobalLocationNumber": "6242000800004",
         "BPName": "شركة أدوية ليبيا لاستيراد الأدوية والمعدات الطبية"
     },
     {
         "GlobalLocationNumber": "6241003540009",
         "BPName": "شركة صانع القهوة لطحن  البن وتحميص المكسرات"
     },
     {
         "GlobalLocationNumber": "6241003550008",
         "BPName": "شركة عدن الليبية لتعبئة المياه والمشروبات والعصائر ذ.م.م"
     },
     {
         "GlobalLocationNumber": "6241003560007",
         "BPName": "شركة طيبة الأنوار لطحن القهوة وتعبئة المكسرات والبقوليات"
     },
     {
         "GlobalLocationNumber": "6241003570006",
         "BPName": "شركة الاثراء العالمية للإستيراد المواد الغذائية"
     },
     {
         "GlobalLocationNumber": "6241003580005",
         "BPName": "شركة الغذاء الطبيعي لتربية النحل وبيع العسل ولوازم تربيته"
     },
     {
         "GlobalLocationNumber": "6241003590004",
         "BPName": "شركة النخبة للاستثمار الصناعي"
     },
     {
         "GlobalLocationNumber": "6241003600000",
         "BPName": "شركة المراد الدائم لاستيراد المواد الغذائية"
     },
     {
         "GlobalLocationNumber": "6241003610009",
         "BPName": "شركة نور التقدم لاستيراد المواد الغذائية"
     },
     {
         "GlobalLocationNumber": "6241003620008",
         "BPName": "شركة امان الغد لاستيراد المواد الغدائية والمواشي واللحوم ذات مس,ولية محدودة"
     },
     {
         "GlobalLocationNumber": "6241003630007",
         "BPName": "شركة ديوان لتعبئة المياه ذات مسؤولية محدودة"
     },
     {
         "GlobalLocationNumber": "6241003640006",
         "BPName": "محل المتفوق للمواد الغذائية"
     },
     {
         "GlobalLocationNumber": "6241003650005",
         "BPName": "شركة دافق لتعبئة المياه"
     },
     {
         "GlobalLocationNumber": "6241003660004",
         "BPName": "شركة روعة للصناعات الغذائية والمشروبات"
     },
     {
         "GlobalLocationNumber": "6241003670003",
         "BPName": "شركة برونتوا للصناعات الغذائية"
     },
     {
         "GlobalLocationNumber": "6241003680002",
         "BPName": "شركة السجاد الاخضر للمواد الغذائية"
     },
     {
         "GlobalLocationNumber": "6241003740003",
         "BPName": "شركة البيزو لصناعة الخبز والخبيز"
     },
     {
         "GlobalLocationNumber": "6241003750002",
         "BPName": "شركة ايفا الجديدة لاستيراد المواد الغذائية"
     },
     {
         "GlobalLocationNumber": "6241003760001",
         "BPName": "شركة البركة الدولية لصناعة الاغذية والمشروبات"
     },
     {
         "GlobalLocationNumber": "6241003770000",
         "BPName": "شركة ميسان لصناعات الغذائية"
     },
     {
         "GlobalLocationNumber": "6241003780009",
         "BPName": "شركة مجموعة فزان"
     },
     {
         "GlobalLocationNumber": "6241003790008",
         "BPName": "شركة بياض الثلج لصناعة المنظفات"
     },
     {
         "GlobalLocationNumber": "6241003800004",
         "BPName": "شركة المحيط الصافي لمعالجة وتعبئة المياه والمشروبات الغازية والعصائر"
     },
     {
         "GlobalLocationNumber": "6241003810003",
         "BPName": "شركة تاج نفوسة لصناعة وتعليب المواد  الغذائية"
     },
     {
         "GlobalLocationNumber": "6241003820002",
         "BPName": "شركة زهرات الربيع لروائح ومواد التنظيف"
     },
     {
         "GlobalLocationNumber": "6241003830001",
         "BPName": "شركة ريفال ليبيا لصناعات الغذائية"
     },
     {
         "GlobalLocationNumber": "6241003840000",
         "BPName": "شركة اكيدة للصناعات الغذائية"
     },
     {
         "GlobalLocationNumber": "6241003850009",
         "BPName": "شركة نوفا للصناعات الغذائية"
     },
     {
         "GlobalLocationNumber": "6241003860008",
         "BPName": "شركة الجوهرة البيضاء للصناعات الغدائية"
     },
     {
         "GlobalLocationNumber": "6241003870007",
         "BPName": "شركة نهر ستيفانس للصناعات الغذائية"
     },
     {
         "GlobalLocationNumber": "6241003880006",
         "BPName": "مصنع الفاخر لصناعة الحلويات"
     },
     {
         "GlobalLocationNumber": "6241003890005",
         "BPName": "شركة الليبية الدولية لصناعة المواد الغذائية"
     },
     {
         "GlobalLocationNumber": "6241003900001",
         "BPName": "شركة البركة للصناعات الغدائية"
     },
     {
         "GlobalLocationNumber": "6241003910000",
         "BPName": "شركة نجيب المدينة للصناعات الغذائية"
     },
     {
         "GlobalLocationNumber": "6241003920009",
         "BPName": "صيدلية المعافاة لتوزيع الادوية والمستلزمات الطبية"
     },
     {
         "GlobalLocationNumber": "6241003930008",
         "BPName": "مطحن بن الصافية لطحن البن"
     },
     {
         "GlobalLocationNumber": "6241003940007",
         "BPName": "شركة الحديقة لاستيراد مواد الزينة والخردوات ومواد التنظيف"
     },
     {
         "GlobalLocationNumber": "6241003950006",
         "BPName": "شركة بريما للصناعات الغذائية"
     },
     {
         "GlobalLocationNumber": "6241003960005",
         "BPName": "شركة ميسان لمواد التنظيف"
     },
     {
         "GlobalLocationNumber": "6241003970004",
         "BPName": "شركة تمام للدواجن واللحوم"
     },
     {
         "GlobalLocationNumber": "6241003980003",
         "BPName": "شركة عفيف لاستيراد المواد الغذائية"
     },
     {
         "GlobalLocationNumber": "6241003990002",
         "BPName": "شركة ياسمين الشام للمنتجات الطبيعية"
     },
     {
         "GlobalLocationNumber": "6241004000007",
         "BPName": "شركة ابي عيسي لتعبئة المياه"
     },
     {
         "GlobalLocationNumber": "6241004010006",
         "BPName": "شركة المجمع الليبي للصناعات الطبية"
     },
     {
         "GlobalLocationNumber": "6241004020005",
         "BPName": "شركة الاخوة المتحدون لصناعة وتعبئة وتغليف مستلزمات الحلويات"
     },
     {
         "GlobalLocationNumber": "6241004030004",
         "BPName": "شركة السحب البيضاء لتنقية وتعبئة مياه الشرب"
     },
     {
         "GlobalLocationNumber": "6241004040003",
         "BPName": "شركة البيفى لتعبئة وصناعة المواد الغدائية"
     },
     {
         "GlobalLocationNumber": "6240000691004",
         "BPName": "شركة الفرن الجديد لصناعة الحلويات"
     },
     {
         "GlobalLocationNumber": "6241004050002",
         "BPName": "شركة مجموعة السهل"
     },
     {
         "GlobalLocationNumber": "6242000900001",
         "BPName": "شركة النجيلة لصناعة البلاستيك"
     },
     {
         "GlobalLocationNumber": "6241004060001",
         "BPName": "شركة الارض المباركة لصناعة الدقيق والاعلاف"
     },
     {
         "GlobalLocationNumber": "6241004070000",
         "BPName": "شركة المتحدة لصناعة الاكواب الورقية"
     },
     {
         "GlobalLocationNumber": "6241004080009",
         "BPName": "شركة ابناء يوسف لصناعة العطور ومواد الزينة"
     },
     {
         "GlobalLocationNumber": "6241004090008",
         "BPName": "شركة زاد العرب للصناعات الغذائية"
     },
     {
         "GlobalLocationNumber": "6241004100004",
         "BPName": "شركة المنتج النفيس لصناعة وتعبئة المواد الغدائية"
     },
     {
         "GlobalLocationNumber": "6241004110003",
         "BPName": "عماد لطحن وتغليف البن"
     },
     {
         "GlobalLocationNumber": "6241004120002",
         "BPName": "مصنع افران زادي للخبز والخبيز"
     },
     {
         "GlobalLocationNumber": "6241004130001",
         "BPName": "رهف الدولية للتعهدات والتموين"
     },
     {
         "GlobalLocationNumber": "6241004140000",
         "BPName": "شركة الابرام لاستيراد المواد الغذائية"
     },
     {
         "GlobalLocationNumber": "6241004150009",
         "BPName": "شركة صابرينا لصناعة المواد الغذائية"
     },
     {
         "GlobalLocationNumber": "6241004160008",
         "BPName": "شركة الخيزران لصناعة الورق الناعم"
     },
     {
         "GlobalLocationNumber": "6241004170007",
         "BPName": "شركة العزيزية للمطاحن"
     },
     {
         "GlobalLocationNumber": "6241004180006",
         "BPName": "شركة فوار  الكفرة للصناعات الغذائية"
     },
     {
         "GlobalLocationNumber": "6241004190005",
         "BPName": "شركة زهرة الوادي للألبان والصناعات الغذائية"
     },
     {
         "GlobalLocationNumber": "6241004200001",
         "BPName": "شركة المحاصيل الجديدة لحفظ وتوزيع المواد الغذائية"
     },
     {
         "GlobalLocationNumber": "6241004210000",
         "BPName": "شركة الربيع المزهر ذ.م.م"
     },
     {
         "GlobalLocationNumber": "6241004220009",
         "BPName": "شركة الأوراس لتغليف والتعبئة"
     },
     {
         "GlobalLocationNumber": "6241004230008",
         "BPName": "شركة المساندة للصناعات الغذائية"
     },
     {
         "GlobalLocationNumber": "6241004240007",
         "BPName": "شركة اويا للصناعات اللغذائية ذات مسؤولية محدودة"
     },
     {
         "GlobalLocationNumber": "6241004250006",
         "BPName": "شركة شهد المدينة لصناعة المواد الغذائية"
     },
     {
         "GlobalLocationNumber": "6241004260005",
         "BPName": "شركة مجموعة الخليل لصناعة المواد الغذائية"
     },
     {
         "GlobalLocationNumber": "6240000089009",
         "BPName": "مصنع افراح شهريار"
     },
     {
         "GlobalLocationNumber": "6241004270004",
         "BPName": "شركة دفق لاستراد المواد الغدائية والمواشي واللحوم"
     },
     {
         "GlobalLocationNumber": "6241004280003",
         "BPName": "شركة الريادة المتالقة لتعبية وتفليف المواد الغدا"
     },
     {
         "GlobalLocationNumber": "6241004290002",
         "BPName": "شركة إليجانت لصناعة الشكولاته والحلويات"
     },
     {
         "GlobalLocationNumber": "6241004300008",
         "BPName": "شركة مفاز للصناعات البتروكيماوية"
     },
     {
         "GlobalLocationNumber": "6241004310007",
         "BPName": "شركة السادة المتميزون للصناعات الغذائية"
     },
     {
         "GlobalLocationNumber": "6241004320006",
         "BPName": "شركة الراشد للصناعات البلاستيكية"
     },
     {
         "GlobalLocationNumber": "6241004330005",
         "BPName": "شركة الربيع لصناعة الحفاظات والقطن الطبي المساهمة"
     },
     {
         "GlobalLocationNumber": "6240000987008",
         "BPName": "شركة التضامن العربي"
     },
     {
         "GlobalLocationNumber": "6242001000007",
         "BPName": "مجمع بني وليد الصناعي"
     },
     {
         "GlobalLocationNumber": "6241004340004",
         "BPName": "مصنع الجودة لحفظ وتغليف المواد الغذائية"
     },
     {
         "GlobalLocationNumber": "6241004350003",
         "BPName": "شركة الغد المقبل للصناعات الغذائية"
     },
     {
         "GlobalLocationNumber": "6241004360002",
         "BPName": "شركة الساحل  لصناعة الحلويات والخبز"
     },
     {
         "GlobalLocationNumber": "6241004370001",
         "BPName": "شركة  التمور الذهبية لانناج وتصنيع التمور"
     },
     {
         "GlobalLocationNumber": "6241004380000",
         "BPName": "شركة الحسام لصناعات الغدائية"
     },
     {
         "GlobalLocationNumber": "6241004390009",
         "BPName": "شركة الريان الوطنية لصناعة وتعبئة المياه والمشروبات"
     },
     {
         "GlobalLocationNumber": "6241004400005",
         "BPName": "شركة جودة الخامات  للصناعات الغدائية"
     },
     {
         "GlobalLocationNumber": "6241004410004",
         "BPName": "شركة أبار أويا لتنقية مياه الشرب"
     },
     {
         "GlobalLocationNumber": "6241004420003",
         "BPName": "شركة محاصيل ليبيا الدولية للصناعات الغدائية"
     },
     {
         "GlobalLocationNumber": "6241004430002",
         "BPName": "شركة لبيكا للصناعات الغدائية"
     },
     {
         "GlobalLocationNumber": "6240000091002",
         "BPName": "تشاركية المجد للصناعات الغذائية"
     },
     {
         "GlobalLocationNumber": "62441004440001",
         "BPName": "شركة النجمة الذهبية للصناعات الغذائية ذ.م.م"
     },
     {
         "GlobalLocationNumber": "6241004450000",
         "BPName": "شركة خيرات المتوسط الحديثة لصناعة وتعبئة المواد الغدائية"
     },
     {
         "GlobalLocationNumber": "6241004460009",
         "BPName": "مطحن النسيم للبن والتوابل والمكسرات"
     },
     {
         "GlobalLocationNumber": "6241004470008",
         "BPName": "شركة قوت ليبيا للأنتاج الاستثماري والزراعي"
     },
     {
         "GlobalLocationNumber": "6241004480007",
         "BPName": "شركة النبراس لتعبئة وتغليف المواد الغدائية"
     },
     {
         "GlobalLocationNumber": "6241004490006",
         "BPName": "شركة البساتين لصناعة المعجون الطماطم والمواد  الغذائية"
     },
     {
         "GlobalLocationNumber": "6241004500002",
         "BPName": "شركة الوفير لصناعة المواد الغذائية المساهمة"
     },
     {
         "GlobalLocationNumber": "6241004510001",
         "BPName": "شركة المدينة الاولي لتعبئة وتغليف المواد الغذائية"
     },
     {
         "GlobalLocationNumber": "6241004520004",
         "BPName": "شركة ياسمين طرابلس لصناعات الورقية"
     },
     {
         "GlobalLocationNumber": "6241004530009",
         "BPName": "شركة السرايا الحديثة لصناعة السجاد"
     },
     {
         "GlobalLocationNumber": "6241004540008",
         "BPName": "شركة ربوع الوادي لصناعة المواد لغذائية وتعبئتها"
     },
     {
         "GlobalLocationNumber": "6240000094003",
         "BPName": "شركة المشرق للصناعات الغذائية"
     },
     {
         "GlobalLocationNumber": "6240000096007",
         "BPName": "مصنع المائدة للصناعات الغذائية"
     },
     {
         "GlobalLocationNumber": "6240000098001",
         "BPName": "تشاركية جالو للصناعات الغذائية"
     },
     {
         "GlobalLocationNumber": "6240000099008",
         "BPName": "مناحل الشفاء"
     },
     {
         "GlobalLocationNumber": "6240000102005",
         "BPName": "شركة العين لتنقية وتعبئة المياه المساهمة"
     },
     {
         "GlobalLocationNumber": "6240000104009",
         "BPName": "شركة المنصور لصناعة حفاظات الاطفال"
     },
     {
         "GlobalLocationNumber": "6240000107000",
         "BPName": "مصنع الصفوة لصناعة المواد الغذائية"
     },
     {
         "GlobalLocationNumber": "6241000250000",
         "BPName": "تشاركية الشمال"
     },
     {
         "GlobalLocationNumber": "6240000117009",
         "BPName": "تشاركية فيصل لطحن البن والحبوب والتوابل"
     },
     {
         "GlobalLocationNumber": "6240000118006",
         "BPName": "شركة أمل لصناعة الروائح ذات المسؤولية المحدودة"
     },
     {
         "GlobalLocationNumber": "6240000119003",
         "BPName": "معمل الصقور لصناعة المشروبات المركزة والمياة"
     },
     {
         "GlobalLocationNumber": "6241000280007",
         "BPName": "مطحن الغلال للتوابل والمكسرات والبقوليات"
     },
     {
         "GlobalLocationNumber": "6241000290006",
         "BPName": "شركة المثلثات للصناعات الغذائية"
     },
     {
         "GlobalLocationNumber": "6240000123000",
         "BPName": "مصنع الفرات لمعالجة وتعبئة المياه"
     },
     {
         "GlobalLocationNumber": "6240000126001",
         "BPName": "مصنع صحة لتعبئة المياه"
     },
     {
         "GlobalLocationNumber": "6240000127008",
         "BPName": "شركة الأميرة ذات المسؤولية المحدودة"
     },
     {
         "GlobalLocationNumber": "6240000131005",
         "BPName": "مطحن الجندي لطحن البن والمكسرات"
     },
     {
         "GlobalLocationNumber": "6240000134006",
         "BPName": "شركة النحلة لصناعة الحلويات"
     },
     {
         "GlobalLocationNumber": "6240000135003",
         "BPName": "مصنع الشراع لصناعة الاكواب والمنتجات الورقية"
     },
     {
         "GlobalLocationNumber": "6240000137007",
         "BPName": "تشاركية الواحات الثلاث"
     },
     {
         "GlobalLocationNumber": "6240000139001",
         "BPName": "شركة الخليج لصناعة وتغليف المكرونة والكسكسى"
     },
     {
         "GlobalLocationNumber": "6240000141004",
         "BPName": "تشاركية لبدة للصناعات الغذائية"
     },
     {
         "GlobalLocationNumber": "6241000300002",
         "BPName": "شركة ثالجة لصناعة المثلجات"
     },
     {
         "GlobalLocationNumber": "6240000150006",
         "BPName": "تشاركية المجموعة لصناعة المثلجات"
     },
     {
         "GlobalLocationNumber": "6240000154004",
         "BPName": "مطحن علاء للبن والتوابل"
     },
     {
         "GlobalLocationNumber": "6240000155001",
         "BPName": "مطحن خالد علي العريبي"
     },
     {
         "GlobalLocationNumber": "6240000157005",
         "BPName": "شركة الدرة للمنتجات الغذائية"
     },
     {
         "GlobalLocationNumber": "6240000161002",
         "BPName": "مصنع شهر زاد لصناعة المثلجات"
     },
     {
         "GlobalLocationNumber": "6240000169008",
         "BPName": "مصنع رواسي لصناعة العصائر"
     },
     {
         "GlobalLocationNumber": "6240000170004",
         "BPName": "شركة الشرق لصناعة المناديل الورقية"
     },
     {
         "GlobalLocationNumber": "6241000310001",
         "BPName": "شركة الحديقة للصناعات الغذائية"
     },
     {
         "GlobalLocationNumber": "6240000173005",
         "BPName": "مطحن النجوم للبن والتوابل والحبوب والمكسرات"
     },
     {
         "GlobalLocationNumber": "6240000176006",
         "BPName": "شركة النجمة لتكرير وتعبئة الزيوت النباتية"
     },
     {
         "GlobalLocationNumber": "6240000179007",
         "BPName": "مصنع تاله لصناعة الورق الناعم"
     },
     {
         "GlobalLocationNumber": "6240000183004",
         "BPName": "شركة الصفوة لتعبئة المياه (بنغازي)"
     },
     {
         "GlobalLocationNumber": "6240000184001",
         "BPName": "شركة كندة للصناعات الغذائية"
     },
     {
         "GlobalLocationNumber": "6240000187002",
         "BPName": "مصنع كوالا كولا للمشروبات"
     },
     {
         "GlobalLocationNumber": "6240000189006",
         "BPName": "شركة المتميز لطحن البن و المكسرات"
     },
     {
         "GlobalLocationNumber": "6240000191009",
         "BPName": "مخبز الحرابي للخبز والخبيز"
     },
     {
         "GlobalLocationNumber": "6240000192006",
         "BPName": "مصنع الزينة لصناعة العصائر والمشروبات الغازية"
     },
     {
         "GlobalLocationNumber": "6240000193003",
         "BPName": "شركة العوافي لتعبئة المياه والمشروبات الغازية"
     },
     {
         "GlobalLocationNumber": "6240000197001",
         "BPName": "مصنع الاسرة المنتجة لصناعة رب الثمر"
     },
     {
         "GlobalLocationNumber": "6240000199005",
         "BPName": "شركة دانة البحر للخبيز ومشتقاته"
     },
     {
         "GlobalLocationNumber": "6240000200008",
         "BPName": "شركة الانماء للصناعات الهندسية المساهمة"
     },
     {
         "GlobalLocationNumber": "6240000208004",
         "BPName": "تشاركية العافية لتعبئة المياه"
     },
     {
         "GlobalLocationNumber": "6240000214005",
         "BPName": "مصنع الجوري لصناعة المناديل الورقية"
     },
     {
         "GlobalLocationNumber": "6240000220006",
         "BPName": "مصنع الاميرة لصناعة المكرونة"
     },
     {
         "GlobalLocationNumber": "6240000226008",
         "BPName": "شركة الجودة الراقية للصناعات الغذائية"
     },
     {
         "GlobalLocationNumber": "6241000350007",
         "BPName": "تشاركية اصيلة لصناعة الحلويات والحلوى الشامية 2"
     },
     {
         "GlobalLocationNumber": "6240000231002",
         "BPName": "الشركة الليبية للتبغ المساهمة"
     },
     {
         "GlobalLocationNumber": "6240000232009",
         "BPName": "تشاركية الراوي لصناعة الألبان ومشتقاتها"
     },
     {
         "GlobalLocationNumber": "6240000233006",
         "BPName": "مصنع نبع صافية لتعبئة المياه"
     },
     {
         "GlobalLocationNumber": "6240000234003",
         "BPName": "مصنع عافية لتعبئة المياه"
     },
     {
         "GlobalLocationNumber": "6240000236007",
         "BPName": "تشاركية الياقوتة لصناعة المناديل والأكواب الورقية"
     },
     {
         "GlobalLocationNumber": "6240000237004",
         "BPName": "مصنع حامل المسك لصناعة الروائح والزيوت والعطور"
     },
     {
         "GlobalLocationNumber": "6240000240004",
         "BPName": "تشاركية فرح للألبان ومشتقاتها"
     },
     {
         "GlobalLocationNumber": "6240000242008",
         "BPName": "تشاركية الحجاج للصناعات الغذائية"
     },
     {
         "GlobalLocationNumber": "6240000244002",
         "BPName": "تشاركية سنابل البركة للخبز والخبيز والمعجنات"
     },
     {
         "GlobalLocationNumber": "6240000247003",
         "BPName": "شركة القواعد الراسخة لصناعة المواد الغذائية"
     },
     {
         "GlobalLocationNumber": "6240000249007",
         "BPName": "مصنع لمة الأسرة لتعبئة المواد الغذائية"
     },
     {
         "GlobalLocationNumber": "6240000250003",
         "BPName": "شركة القرية المتحدة لصناعة وتعليب المواد الغذائية"
     },
     {
         "GlobalLocationNumber": "6240000251000",
         "BPName": "مصنع الواحة لتعبئة وتنقية مياه الشرب"
     },
     {
         "GlobalLocationNumber": "6240000252007",
         "BPName": "مصنع الربيع لتعبئة المياه المعدنية والغازية"
     },
     {
         "GlobalLocationNumber": "6241000370005",
         "BPName": "شركة الرحبة لإستيراد المواد الغذائية"
     },
     {
         "GlobalLocationNumber": "6240000254001",
         "BPName": "شركة الابيار لانتاج الدقيق ومشتقاته"
     },
     {
         "GlobalLocationNumber": "6240000257002",
         "BPName": "مطحن البركة لصناعة القهوة"
     },
     {
         "GlobalLocationNumber": "6240000260002",
         "BPName": "شركة العشاب لإستخلاص وتعبئة الزيوت والمنتجات الطبيعية"
     },
     {
         "GlobalLocationNumber": "6240000261009",
         "BPName": "مصنع جزيرة بسيس لتعبئة المياه المعدنية"
     },
     {
         "GlobalLocationNumber": "6240000262006",
         "BPName": "مطحن البرازيل للقهوة"
     },
     {
         "GlobalLocationNumber": "6240000263003",
         "BPName": "تشاركية مطاحن لبدة للبن والتوابل والبقوليات"
     },
     {
         "GlobalLocationNumber": "6241000390003",
         "BPName": "مصنع السندباد لصناعة وتعبئة المواد الغذائية"
     },
     {
         "GlobalLocationNumber": "6241000400009",
         "BPName": "شركة الهواري لإستيراد وتصدير المواد الغذائية"
     },
     {
         "GlobalLocationNumber": "6240000266004",
         "BPName": "تشاركية انوار المدينة لإنتاج الاكياس البلاستيكية"
     },
     {
         "GlobalLocationNumber": "6240000272005",
         "BPName": "مطحن ابناء سالم الزمزام"
     },
     {
         "GlobalLocationNumber": "6240000275006",
         "BPName": "مصنع الصفاء للألبان ومشتقاتها"
     },
     {
         "GlobalLocationNumber": "6240000278007",
         "BPName": "شركة عسل الشفاء لمنتجات النحل المحدودة"
     },
     {
         "GlobalLocationNumber": "6240000283001",
         "BPName": "تشاركية قصر الحلوى الجديد"
     },
     {
         "GlobalLocationNumber": "6240000284008",
         "BPName": "مصنع نبع الحياة"
     },
     {
         "GlobalLocationNumber": "6240000286002",
         "BPName": "مصنع الانتصار للمشروبات المركزة"
     },
     {
         "GlobalLocationNumber": "6240000287009",
         "BPName": "شركة الفوز الصناعية المساهمة لطحن الاغلال وانتاج الدقيق"
     },
     {
         "GlobalLocationNumber": "6240000288006",
         "BPName": "مصنع رنا للحلويات"
     },
     {
         "GlobalLocationNumber": "6240000289003",
         "BPName": "تشاركية السنبلة الذهبية لصناعة الخبيز"
     },
     {
         "GlobalLocationNumber": "6240000293000",
         "BPName": "شركة بابل لتعبئة مياة الشرب والعصائر"
     },
     {
         "GlobalLocationNumber": "6240000294007",
         "BPName": "تشاركيّة القور لإنتاج وتصنيع التّمور"
     },
     {
         "GlobalLocationNumber": "6240000300005",
         "BPName": "مطحن النجمة للقهوة والسكر الناعم"
     },
     {
         "GlobalLocationNumber": "6240000303006",
         "BPName": "تشاركية الزاد الوافر لصناعة المواد الغذائية"
     },
     {
         "GlobalLocationNumber": "6240000305000",
         "BPName": "التشاركية الوطنية لصناعة الحفاضات والورق الناعم"
     },
     {
         "GlobalLocationNumber": "6240000310004",
         "BPName": "مصنع البستان لصناعة الالبان ومشتقاتها"
     },
     {
         "GlobalLocationNumber": "6240000312008",
         "BPName": "شركة تاجوراء للصناعات الغذائية"
     },
     {
         "GlobalLocationNumber": "6240000313005",
         "BPName": "شركة المواد الصحية لصناعة القطن الصحي"
     },
     {
         "GlobalLocationNumber": "6240000315009",
         "BPName": "مصنع الجودة لصناعة المواد المنزلية"
     },
     {
         "GlobalLocationNumber": "6240000316006",
         "BPName": "شركة البساتين لصناعة المناديل الورقية"
     },
     {
         "GlobalLocationNumber": "6240000319007",
         "BPName": "شركة الضيافة الليبية لصناعة المواد الغدائية و المشروبات"
     },
     {
         "GlobalLocationNumber": "6241000410008",
         "BPName": "شركة الأندلس لتعبئة وتغليف وحفظ المواد الغذائية ذات المسؤولية المحدودة"
     },
     {
         "GlobalLocationNumber": "6240000323004",
         "BPName": "مصنع أبار جيرة لتعبئة المياه"
     },
     {
         "GlobalLocationNumber": "6240000325008",
         "BPName": "مصنع منابع الخير للمخلالات"
     },
     {
         "GlobalLocationNumber": "6241000420007",
         "BPName": "شركة المدينة للصناعات الدوائية"
     },
     {
         "GlobalLocationNumber": "6241000430006",
         "BPName": "شركة الريشة الذهبية لاستيراد المواد الغذائية المساهمة"
     },
     {
         "GlobalLocationNumber": "6240000327002",
         "BPName": "مصنع الهناء لمعالجة وتعبئة المياه"
     },
     {
         "GlobalLocationNumber": "6240000328009",
         "BPName": "شركة الهناء لتنقية وتعبئة مياه الشرب ذات المسؤولية المحدودة"
     },
     {
         "GlobalLocationNumber": "6240000329006",
         "BPName": "تشاركية الأمانة لإستيراد مواد التنظيف و مواد الزّينة"
     },
     {
         "GlobalLocationNumber": "6240000330002",
         "BPName": "شركة وادي الربيع لإنتاج الدقيق ومشتقّاتة"
     },
     {
         "GlobalLocationNumber": "6240000332006",
         "BPName": "مصنع قطر النداء لتنقية ومعالجة المياه"
     },
     {
         "GlobalLocationNumber": "6240000334000",
         "BPName": "شركة الفائدة للصناعات الغذائية"
     },
     {
         "GlobalLocationNumber": "6240000335007",
         "BPName": "شركة الحصاد لطحن الحبوب وانتاج الدقيق ومشتقاته المساهمة"
     },
     {
         "GlobalLocationNumber": "6240000337001",
         "BPName": "مطحن اليُمن (1)  للقهوة والسكرالناعم والمكسرات"
     },
     {
         "GlobalLocationNumber": "6240000338008",
         "BPName": "شركة الجليد لصناعة الصابون ومواد التنظيف ذات المسؤولية المحدودة"
     },
     {
         "GlobalLocationNumber": "6240000339005",
         "BPName": "شركة مجمع المشرق للصناعات الغذائية"
     },
     {
         "GlobalLocationNumber": "6240000340001",
         "BPName": "مطحن اليُمن 2 للقهوة والسكر الناعم"
     },
     {
         "GlobalLocationNumber": "6240000341008",
         "BPName": "مطحن غريب للبن"
     },
     {
         "GlobalLocationNumber": "6240000342005",
         "BPName": "مصنع مزرعتي للصناعات الغذائية"
     },
     {
         "GlobalLocationNumber": "6240000343002",
         "BPName": "شركة الخيرات للصناعات الغذائية ذات المسؤلية المحدودة"
     },
     {
         "GlobalLocationNumber": "6240000344009",
         "BPName": "شركة الحقول لاستيراد المواد الغذائية المساهمة"
     },
     {
         "GlobalLocationNumber": "6241000460003",
         "BPName": "مطحن بوشريقة لتعليب وتغليف المواد الغذائية"
     },
     {
         "GlobalLocationNumber": "6240000345006",
         "BPName": "شركة ايثار للصناعات الغذائية المساهمة"
     },
     {
         "GlobalLocationNumber": "6240000346003",
         "BPName": "شركة الفرناج للصناعات الغذائية"
     },
     {
         "GlobalLocationNumber": "6240000347000",
         "BPName": "معصرة الشجرة المباركة لعصر الزيتون"
     },
     {
         "GlobalLocationNumber": "6240000348007",
         "BPName": "شركة الجديدة لتعبئة المياه ذات مسئولية محدودة"
     },
     {
         "GlobalLocationNumber": "6240000350000",
         "BPName": "شركة البشير للطحن التوابل والبن وتعليب المواد الغذائية"
     },
     {
         "GlobalLocationNumber": "6240000351007",
         "BPName": "الجودة الاصلية لصناعة وتعبئة المواد الغذائية"
     },
     {
         "GlobalLocationNumber": "6240000353001",
         "BPName": "محل ربان للتعبئة والتغليف"
     },
     {
         "GlobalLocationNumber": "6240000354008",
         "BPName": "شركة افران السرايا لصناعة الحلويات والخبيز ذات مسئولية محدودة"
     },
     {
         "GlobalLocationNumber": "6240000355005",
         "BPName": "شركة البيلسان لصناعة المناديل الورقية المبللة والمعطرة"
     },
     {
         "GlobalLocationNumber": "6240000356002",
         "BPName": "شركة المسك لصناعة الورق وأكواب الورقية ذات مسئولية محدودة"
     },
     {
         "GlobalLocationNumber": "6241000450004",
         "BPName": "شركة الفضة لصناعة وحفظ الاغذية ذات المسئولية المحدودة"
     },
     {
         "GlobalLocationNumber": "6240000358006",
         "BPName": "شركة الوديان لتنقية وتحلية المياه"
     },
     {
         "GlobalLocationNumber": "6240000359003",
         "BPName": "شركة كنزك ليبيا لاستيراد الملابس ومواد التنظيف والتعقيم"
     },
     {
         "GlobalLocationNumber": "6240000360009",
         "BPName": "شركة الرواق للصناعات البلاستكية"
     },
     {
         "GlobalLocationNumber": "6240000361006",
         "BPName": "مصنع زين للورق الناعم"
     },
     {
         "GlobalLocationNumber": "6240000362003",
         "BPName": "شركة الصداقة المثالية للصناعات الغذائية"
     },
     {
         "GlobalLocationNumber": "6240000363000",
         "BPName": "شركة السهلة لتعبئة المياه والمشروبات"
     },
     {
         "GlobalLocationNumber": "6240000364007",
         "BPName": "مطحن كراكاس للبن"
     },
     {
         "GlobalLocationNumber": "6240000365004",
         "BPName": "مطحن توباكتس"
     },
     {
         "GlobalLocationNumber": "6240000366001",
         "BPName": "شركة الجزيرة لاستيراد المواد الغذائية"
     },
     {
         "GlobalLocationNumber": "6240000367008",
         "BPName": "مصنع الفيحاء لتعبئة المياه"
     },
     {
         "GlobalLocationNumber": "6240000368005",
         "BPName": "مصنع الساحل لتحلية وتعبئة المياه"
     },
     {
         "GlobalLocationNumber": "6240000370008",
         "BPName": "شركة النقاء الابيض لصناعة المناديل الورقية"
     },
     {
         "GlobalLocationNumber": "6240000372002",
         "BPName": "مصنع الفانوس للبن والمكسرات"
     },
     {
         "GlobalLocationNumber": "6241000470002",
         "BPName": "حلواني معتز بوعشرين"
     },
     {
         "GlobalLocationNumber": "6240000374006",
         "BPName": "مصنع سما ليبيا لتعبئة المياه"
     },
     {
         "GlobalLocationNumber": "6240000375003",
         "BPName": "شركة الأبدية لتعبئة المياه والعصائر"
     },
     {
         "GlobalLocationNumber": "6240000376000",
         "BPName": "شركة السرايا الحمراء لاستيراد البن والحبوب"
     },
     {
         "GlobalLocationNumber": "6241000480001",
         "BPName": "شركة الندى لتصنيع وتعبئة و تغليف المواد الغدائية"
     },
     {
         "GlobalLocationNumber": "6241000490000",
         "BPName": "مصنع مقالي ومطاحن البن والتوابل والحبوب"
     },
     {
         "GlobalLocationNumber": "6240000377007",
         "BPName": "شركة الروضة للصناعات الغذائية"
     },
     {
         "GlobalLocationNumber": "6240000378004",
         "BPName": "مصنع التركى لصناعة الالبان ومنتجاتها"
     },
     {
         "GlobalLocationNumber": "6240000379001",
         "BPName": "مصنع المزن لتعبئة وتنقية المياه"
     },
     {
         "GlobalLocationNumber": "6240000380007",
         "BPName": "شركة الخليج لتعبئة المياه والمشروبات"
     },
     {
         "GlobalLocationNumber": "6240000381004",
         "BPName": "مصنع نبيل عبدالمجيد محمد عامر"
     },
     {
         "GlobalLocationNumber": "6241000500006",
         "BPName": "شركة المراعي الليبية للصناعات الغذائية 2"
     },
     {
         "GlobalLocationNumber": "6240000382001",
         "BPName": "شركة كنوز لتعبئة المياه"
     },
     {
         "GlobalLocationNumber": "6240000383008",
         "BPName": "شركة الطاقم للصناعات الغذائية"
     },
     {
         "GlobalLocationNumber": "6240000384005",
         "BPName": "مصنع زلال لتعبئة المياه"
     },
     {
         "GlobalLocationNumber": "6240000385002",
         "BPName": "الشركة الحديثة المساهمة لاستيراد المواد الغذائية"
     },
     {
         "GlobalLocationNumber": "6240000386009",
         "BPName": "شركة صابرين لتعبئة مياه الشرب"
     },
     {
         "GlobalLocationNumber": "6240000387006",
         "BPName": "شركة الوابل لتنقية وتعبئة المياه"
     },
     {
         "GlobalLocationNumber": "6240000388003",
         "BPName": "مصنع القطرات لتحلية وتعبئة المياه"
     },
     {
         "GlobalLocationNumber": "6240000389000",
         "BPName": "مصنع القبائلي لمواد التنظيف بجميع انواعها"
     },
     {
         "GlobalLocationNumber": "6240000390006",
         "BPName": "مصنع النبع الصافي"
     },
     {
         "GlobalLocationNumber": "6240000391003",
         "BPName": "شركة نبع المسرة لتعبئة الياه والمشروبات ذ م م"
     },
     {
         "GlobalLocationNumber": "6240000392000",
         "BPName": "شركة زيتونة ليبيا لاستراد المواد الغذائية"
     },
     {
         "GlobalLocationNumber": "6241000510005",
         "BPName": "شركة البركة لتكرير وتعبئة الزيوت النباتية 2"
     },
     {
         "GlobalLocationNumber": "6240000393007",
         "BPName": "مصنع ديمة للمشروبات وتنقية ومعالجة المياه"
     },
     {
         "GlobalLocationNumber": "6240000394004",
         "BPName": "شركة انمار لتعبئة وتغليف المواد الغذائية"
     },
     {
         "GlobalLocationNumber": "6240000396008",
         "BPName": "شركة الربيع العربي للصناعات الغذائية وتعبئة المياه"
     },
     {
         "GlobalLocationNumber": "6240000397005",
         "BPName": "شركة المودة للمشروبات"
     },
     {
         "GlobalLocationNumber": "6240000398002",
         "BPName": "مطحن رُبي للبن والتوابل"
     },
     {
         "GlobalLocationNumber": "6241000530003",
         "BPName": "شركة الارض للصناعات الغذائية-2"
     },
     {
         "GlobalLocationNumber": "6240000400002",
         "BPName": "شركة الشهد لصناعة التبغ"
     },
     {
         "GlobalLocationNumber": "6240000401009",
         "BPName": "شركة نقل التقنية لتصنيع الكيماويات"
     },
     {
         "GlobalLocationNumber": "6240000402006",
         "BPName": "مصنع أكياس بلاستيكية"
     },
     {
         "GlobalLocationNumber": "6240000403003",
         "BPName": "شركة شيماء للصناعات الغذائية ذ م م"
     },
     {
         "GlobalLocationNumber": "6241000540002",
         "BPName": "الشركة الليبة لصناعة وتعليب الاسماك"
     },
     {
         "GlobalLocationNumber": "6241001420006",
         "BPName": "تشاركية النجمة لصناعة الصابون ومواد التنظيف 2"
     },
     {
         "GlobalLocationNumber": "6240000404000",
         "BPName": "شركة الساقي لتحلية المياه"
     },
     {
         "GlobalLocationNumber": "6240000405007",
         "BPName": "مصنع المنبع لتحلية المياه"
     },
     {
         "GlobalLocationNumber": "6240000406004",
         "BPName": "شركة الاندلس لصناعة المثلجات والمواد الغذائية"
     },
     {
         "GlobalLocationNumber": "6240000407001",
         "BPName": "شركة الاخوة لتعبئة وتغليف المواد الغذائية"
     },
     {
         "GlobalLocationNumber": "6240000408008",
         "BPName": "شركة الزاد الطيب لصناعة الدقيق"
     },
     {
         "GlobalLocationNumber": "6240000409005",
         "BPName": "مصنع الشط لتعبئة وتغليف البقوليات"
     },
     {
         "GlobalLocationNumber": "6240000410001",
         "BPName": "مطحن ابناء المصوكي"
     },
     {
         "GlobalLocationNumber": "6240000411008",
         "BPName": "شركة المزن النافع للصناعات الغذائية"
     },
     {
         "GlobalLocationNumber": "6240000412005",
         "BPName": "شركة الكيس للصناعات البلاستيكية"
     },
     {
         "GlobalLocationNumber": "6240000413002",
         "BPName": "مطحن الجودة للبن"
     },
     {
         "GlobalLocationNumber": "6242000000008",
         "BPName": "شركة مجموعة الفخامة لأستيراد الملابس والمنسوجات و المواد الغذائية والاثاث والادوات المنزلية"
     },
     {
         "GlobalLocationNumber": "6240000414009",
         "BPName": "شركة الفيض لتنقية وتعبئة المياه"
     },
     {
         "GlobalLocationNumber": "6240000415006",
         "BPName": "شركة واحة الماء لتحلية وتعبئة المياه"
     },
     {
         "GlobalLocationNumber": "6240000416003",
         "BPName": "شركة الصحة لتحلية وتعبئة المياه"
     },
     {
         "GlobalLocationNumber": "6240000417000",
         "BPName": "شركة سما لصناعة وتعبئة المياه"
     },
     {
         "GlobalLocationNumber": "6240000418007",
         "BPName": "شركة النعمة لعصر وتعليب وتكرير الزيوت"
     },
     {
         "GlobalLocationNumber": "6240000419004",
         "BPName": "مصنع المحيط لتغليف وتعبئة الحبوب والتوابل"
     },
     {
         "GlobalLocationNumber": "6240000420000",
         "BPName": "مطحن الحبوب والتوابل وتعبئتها"
     },
     {
         "GlobalLocationNumber": "6240000422004",
         "BPName": "شركة تميمة لتنقية وتحلية المياه ذ.م.م"
     },
     {
         "GlobalLocationNumber": "6240000423001",
         "BPName": "شركة اليزيد لتعبئة وتغليف المواد الغذائية"
     },
     {
         "GlobalLocationNumber": "6240000424008",
         "BPName": "مصنع الصفاء لصناعة الحلويات والحلقوم"
     },
     {
         "GlobalLocationNumber": "6240000426002",
         "BPName": "مصنع المياه العذبة لتعبئة وتغليف المياه"
     },
     {
         "GlobalLocationNumber": "6240000427009",
         "BPName": "شركة السرايا الحمراء للصناعات الغذائية"
     },
     {
         "GlobalLocationNumber": "6240000428006",
         "BPName": "مصنع الضيافة للحلويات والمثلجات"
     },
     {
         "GlobalLocationNumber": "6240000429003",
         "BPName": "مخبز الفوانيس للخبز والخبيز"
     },
     {
         "GlobalLocationNumber": "6240000430009",
         "BPName": "شركة مصراته للصناعات الغذائية"
     },
     {
         "GlobalLocationNumber": "6240000431006",
         "BPName": "شركة البرزخ لتعبئة المياه والمشروبات الغازيه المحدوده"
     },
     {
         "GlobalLocationNumber": "6240000432003",
         "BPName": "شركة رواسي الخليج لصناعة المواد الغذائية ذات المسؤولية المحدودة"
     },
     {
         "GlobalLocationNumber": "6240000434007",
         "BPName": "مصنع صحة لتعبئة وتغليف المواد الغذائية"
     },
     {
         "GlobalLocationNumber": "6240000435004",
         "BPName": "شركة السعادة لصناعة المواد الغذائية ذات المسؤولية المحدودة"
     },
     {
         "GlobalLocationNumber": "6240000436001",
         "BPName": "مصنع الزيتونة لصناعة الحلويات"
     },
     {
         "GlobalLocationNumber": "6240000437008",
         "BPName": "مصنع الزاد لصناعة البسكويت والشكلاطة"
     },
     {
         "GlobalLocationNumber": "6240000438005",
         "BPName": "شركة المائدة الصافية لتحلية المياه وتعبئة المشروبات ذ.م.م"
     },
     {
         "GlobalLocationNumber": "6240000440008",
         "BPName": "مخبز عبد الحكيم قرواش"
     },
     {
         "GlobalLocationNumber": "6240000441005",
         "BPName": "شركة أرزاق لتعبئة وصناعة المياه والمشروبات والمواد الغذائية"
     },
     {
         "GlobalLocationNumber": "6241000550001",
         "BPName": "شركة الموقد لاستيراد المواد المنزلية والكهربائية"
     },
     {
         "GlobalLocationNumber": "6240000442002",
         "BPName": "شركة مرمره لاستيراد المواد الغذائية"
     },
     {
         "GlobalLocationNumber": "6240000443009",
         "BPName": "شركة الخيرات الليبية لصناعة المواد الغذائية"
     },
     {
         "GlobalLocationNumber": "6240000444006",
         "BPName": "شركة الثقة لصناعات المواد الغذائية"
     },
     {
         "GlobalLocationNumber": "6241000560000",
         "BPName": "مطحن بوعود"
     },
     {
         "GlobalLocationNumber": "6240000445003",
         "BPName": "شركة سكره لصناعة الحلويات"
     },
     {
         "GlobalLocationNumber": "6240000446000",
         "BPName": "مصنع طيبة لمستحضرات العناية بالجسم 2"
     },
     {
         "GlobalLocationNumber": "6240000447007",
         "BPName": "مصنع السنبلة لصناعة العصائر والعطور والخل"
     },
     {
         "GlobalLocationNumber": "6241000570009",
         "BPName": "شركة اللؤلؤة لإستيراد المواد المنزلية"
     },
     {
         "GlobalLocationNumber": "6240000449001",
         "BPName": "شركة تازيري لاستيراد المواد الغذائية والفواكه الطازجة"
     },
     {
         "GlobalLocationNumber": "6240000450007",
         "BPName": "شركة الربيع الدائم للصناعات الغذائية وتعبئة المياه والمشروبات الغازية"
     },
     {
         "GlobalLocationNumber": "6240000452001",
         "BPName": "شركة الاكليل لصناعه المواد الغذائية"
     },
     {
         "GlobalLocationNumber": "6240000453008",
         "BPName": "مصنع المورد لتنقية وتعبئة المياه"
     },
     {
         "GlobalLocationNumber": "6240000455002",
         "BPName": "شركة التحدي الخالد للمطاحن والأعلاف"
     },
     {
         "GlobalLocationNumber": "6240000456009",
         "BPName": "شركة العيون لتعبئة المياه"
     },
     {
         "GlobalLocationNumber": "6240000457006",
         "BPName": "شركة الصياد لتعبئة وتنقية المياه والمشروبات"
     },
     {
         "GlobalLocationNumber": "6240000458003",
         "BPName": "شركة الاتقان الدولية للصناعات الغذائية وتعبئة المياه والمشروبات"
     },
     {
         "GlobalLocationNumber": "6240000459000",
         "BPName": "مصنع الطاهر السنوسي للمعجنات"
     },
     {
         "GlobalLocationNumber": "6240000460006",
         "BPName": "مصنع المدينة لتعبئة ومعالجة مياه الشرب"
     },
     {
         "GlobalLocationNumber": "6240000462000",
         "BPName": "شركة مزن السلام لتعبئة المياه الصحية والمشروبات"
     },
     {
         "GlobalLocationNumber": "6240000463007",
         "BPName": "شركة قطر الندي لتعبئة المياه والمشروبات الغازية"
     },
     {
         "GlobalLocationNumber": "6241000580008",
         "BPName": "شركة الريادة للصناعات الغذائية"
     },
     {
         "GlobalLocationNumber": "6240000464004",
         "BPName": "مصنع الواحة لتعبئة وتنقية المياه"
     },
     {
         "GlobalLocationNumber": "6240000465001",
         "BPName": "شركة النهر الدافق لتعبئة وتنقية المياه والمشروبات"
     },
     {
         "GlobalLocationNumber": "6240000466008",
         "BPName": "شركة الروابي للصناعات الغذائية"
     },
     {
         "GlobalLocationNumber": "6240000467005",
         "BPName": "شركة أصول الآتقان لاستيراد المواد الغذائية"
     },
     {
         "GlobalLocationNumber": "6240000468002",
         "BPName": "شركة الدلة لاستيراد المواد الغذائية"
     },
     {
         "GlobalLocationNumber": "6240000469009",
         "BPName": "شركة روبيانة لتقنية وتعبئة المياه العادية والغازية"
     },
     {
         "GlobalLocationNumber": "6240000471002",
         "BPName": "النخيل العربي لتعبئة وتغليف التمور"
     },
     {
         "GlobalLocationNumber": "6240000472009",
         "BPName": "شركة الخلجان لتعبئة المياه المشروبات"
     },
     {
         "GlobalLocationNumber": "6241000590007",
         "BPName": "شركة زهرة الربيع لأنتاج العسل"
     },
     {
         "GlobalLocationNumber": "6240000473006",
         "BPName": "شركة عين الفرس لصناعة المناديل الورقية"
     },
     {
         "GlobalLocationNumber": "6240000474003",
         "BPName": "شركة التاج الذهبي لصناعة المواد الغذائية"
     },
     {
         "GlobalLocationNumber": "6240000475000",
         "BPName": "شركة إيلاف لصناعة المثلجات و العصائر"
     },
     {
         "GlobalLocationNumber": "6240000477004",
         "BPName": "شركة نور الدولية للصناعات الغذائية"
     },
     {
         "GlobalLocationNumber": "6240000478001",
         "BPName": "شركة الصفوة لتعبئة المياه والمشروبات الغازية"
     },
     {
         "GlobalLocationNumber": "6240000479008",
         "BPName": "شركة الموج لتعبئة المياه والمشروبات الغازية"
     },
     {
         "GlobalLocationNumber": "6240000480004",
         "BPName": "مصنع الواحة لتعبئة المخلالات والزيتون"
     },
     {
         "GlobalLocationNumber": "6240000481001",
         "BPName": "مصنع راما لتعبئة وتنقية المياه"
     },
     {
         "GlobalLocationNumber": "6240000482008",
         "BPName": "مصنع الاجواء لصناعة المناديل المعطرة والورق الناعم"
     },
     {
         "GlobalLocationNumber": "6240000483005",
         "BPName": "تشاركية الاشراف لذبح الدواجن وبيعها"
     },
     {
         "GlobalLocationNumber": "6240000485009",
         "BPName": "مصنع عين الدراهم لتعبئة المياه"
     },
     {
         "GlobalLocationNumber": "6240000486006",
         "BPName": "شركة المنهل للصناعات الغذائية"
     },
     {
         "GlobalLocationNumber": "6240000488000",
         "BPName": "شركة لامار لصناعة المياه والمشروبات"
     },
     {
         "GlobalLocationNumber": "6240000489007",
         "BPName": "شركة الصفاء الأولى للصناعات الغذائية"
     },
     {
         "GlobalLocationNumber": "6240000490003",
         "BPName": "شركة النخبة العالمية لاستيراد المواد الغذائية"
     },
     {
         "GlobalLocationNumber": "6240000491000",
         "BPName": "مصنع يوسف جمعة شعبان بربوش لتعبئة المياه"
     },
     {
         "GlobalLocationNumber": "6240000492007",
         "BPName": "شركة وهيبة وشركاؤه لاستيراد المواد الغذائية والمنزلية والقرطاسية والاثاث"
     },
     {
         "GlobalLocationNumber": "6240000493004",
         "BPName": "شركة الماجن لتحلية المياه"
     },
     {
         "GlobalLocationNumber": "6240000494001",
         "BPName": "شركة زاد النفوس لصناعة الخبيز"
     },
     {
         "GlobalLocationNumber": "6240000495008",
         "BPName": "شركة الممتاز لاستيراد الطلاء ومعداته المساهمة"
     },
     {
         "GlobalLocationNumber": "6240000496005",
         "BPName": "مصنع الاسرة لصناعة الشوكولاتة"
     },
     {
         "GlobalLocationNumber": "6240000497002",
         "BPName": "شركة الندى لصناعة الالبان ومشتقاته"
     },
     {
         "GlobalLocationNumber": "6240000498009",
         "BPName": "شركة الاوراس لتعبئة المياه والمشروبات"
     },
     {
         "GlobalLocationNumber": "6241000600003",
         "BPName": "شركة شمال المتوسط لاستيراد المواد الغذائية المساهمة"
     },
     {
         "GlobalLocationNumber": "6240000499006",
         "BPName": "شركة الشاكر للصناعات الغذائية"
     },
     {
         "GlobalLocationNumber": "6240000500009",
         "BPName": "شركة الوادي لتعبئة المياه"
     },
     {
         "GlobalLocationNumber": "6240000501006",
         "BPName": "محل أبناء الهادئ حمرانة"
     },
     {
         "GlobalLocationNumber": "6240000502003",
         "BPName": "شركة الغفران لتعبئة المياه"
     },
     {
         "GlobalLocationNumber": "6240000504007",
         "BPName": "شركة ماء السماء لتعبئة وتنقية المياه والمشروبات"
     },
     {
         "GlobalLocationNumber": "6240000505004",
         "BPName": "شركة نبع السلاطين لتعبئة المياه والمشروبات"
     },
     {
         "GlobalLocationNumber": "6240000506001",
         "BPName": "شركة الوادي الذهبي لاستيراد المواد الغذائية"
     },
     {
         "GlobalLocationNumber": "6240000507008",
         "BPName": "شركة الجودة الليبية للصناعات الغذائية"
     },
     {
         "GlobalLocationNumber": "6240000508005",
         "BPName": "مصنع البيسان للصناعات الورقية"
     },
     {
         "GlobalLocationNumber": "6240000509002",
         "BPName": "شركة الرونق لتعبئة المياه والمشروبات"
     },
     {
         "GlobalLocationNumber": "6240000510008",
         "BPName": "شركة الجوهرة الذهبية لصناعة المواد الغذائية"
     },
     {
         "GlobalLocationNumber": "6240000511005",
         "BPName": "شركة جنات لتعبئة المياه"
     },
     {
         "GlobalLocationNumber": "6240000512002",
         "BPName": "شركة التاج لصناعة الحلويات والخبيز"
     },
     {
         "GlobalLocationNumber": "6240000513009",
         "BPName": "شركة ليبيا التقدم للخدمات الزراعية"
     },
     {
         "GlobalLocationNumber": "6240000514006",
         "BPName": "شركة النقاء لصناعة المواد الغذائية"
     },
     {
         "GlobalLocationNumber": "6240000515003",
         "BPName": "شركة راس التراب لصناعة المياه المعدنية"
     },
     {
         "GlobalLocationNumber": "6240000517007",
         "BPName": "شركة عين البلاد لاستيراد المواد الغذائية"
     },
     {
         "GlobalLocationNumber": "6240000518004",
         "BPName": "شركة الريان للتعهدات والتموين"
     },
     {
         "GlobalLocationNumber": "6240000519001",
         "BPName": "شركة السفير لصناعة القهوة"
     },
     {
         "GlobalLocationNumber": "6240000520007",
         "BPName": "مطحن الشروق"
     },
     {
         "GlobalLocationNumber": "6240000521004",
         "BPName": "شركة الحرمين للصناعات الغذائية"
     },
     {
         "GlobalLocationNumber": "6240000523008",
         "BPName": "شركة الرتاج لصناعة الاثاث والمفروشات"
     },
     {
         "GlobalLocationNumber": "6240000524005",
         "BPName": "مصنع عبدالله الرسي لتعئبة وتغليف المواد الغذائية"
     },
     {
         "GlobalLocationNumber": "6240000526009",
         "BPName": "شركة سبيل الخير لصناعة المواد الغذائية"
     },
     {
         "GlobalLocationNumber": "6240000527006",
         "BPName": "شركة بئر خالصه"
     },
     {
         "GlobalLocationNumber": "6240000528003",
         "BPName": "شركة نسيم الجبل لتحلية وتعبئة مياة الشرب"
     },
     {
         "GlobalLocationNumber": "6241000610002",
         "BPName": "شركة بغداد للصناعات الدوائية"
     },
     {
         "GlobalLocationNumber": "6240000529000",
         "BPName": "شركة مجموعة الإمتياز للصناعات الغذائية والمطاحن ومضارب الارز"
     },
     {
         "GlobalLocationNumber": "6241000620001",
         "BPName": "شركة مجموعة المتوسط لتغليف المواد الغذائية"
     },
     {
         "GlobalLocationNumber": "6240000530006",
         "BPName": "شركة الساعدية الجديدة لتعبئة المواد الغذائية"
     },
     {
         "GlobalLocationNumber": "6240000531003",
         "BPName": "مصنع الصفاء لتنقية وتعبية مياه الشرب والعصائر"
     },
     {
         "GlobalLocationNumber": "6240000533007",
         "BPName": "شركة الشجرة الطيبة لبيع وتوزيع التمور"
     },
     {
         "GlobalLocationNumber": "6241000630000",
         "BPName": "شركة الاصيل للصناعات الغذائية"
     },
     {
         "GlobalLocationNumber": "6240000534004",
         "BPName": "شركة النجمة الذهبية لصناعة مواد التنظيف"
     },
     {
         "GlobalLocationNumber": "6240000535001",
         "BPName": "مصنع النجمة الذهبية لصناعة المواد المنزلية والاكياس البلاستكية"
     },
     {
         "GlobalLocationNumber": "6240000536008",
         "BPName": "شركة اغادير الدولية لتعبئة المياه"
     },
     {
         "GlobalLocationNumber": "6240000537005",
         "BPName": "مصنع الريان لصناعة الاكواب الورقية"
     },
     {
         "GlobalLocationNumber": "6240000538002",
         "BPName": "شركة ينابيع العين لتعبئة المياه والمشروبات الغازية"
     },
     {
         "GlobalLocationNumber": "6240000539009",
         "BPName": "شركة الرشاح لتعبئة مياه الشرب"
     },
     {
         "GlobalLocationNumber": "6240000540005",
         "BPName": "شركة الواحات لتعبية المياه والمشروبات"
     },
     {
         "GlobalLocationNumber": "6241003690001",
         "BPName": "شركة الحسن للصناعات الغذائية 2"
     },
     {
         "GlobalLocationNumber": "6240000541002",
         "BPName": "شركة العذبة لتعبئة وتنقية المياه والمشروبات"
     },
     {
         "GlobalLocationNumber": "6241000640009",
         "BPName": "شركة نسائم الحياة لتعبئة المياة الشرب والمشروبات والعصائر"
     },
     {
         "GlobalLocationNumber": "6240000542009",
         "BPName": "شركة وعد الخير لصناعة وتعليب المواد الغذائية"
     },
     {
         "GlobalLocationNumber": "6240000543006",
         "BPName": "شركة النهضة الحديثة لصناعة البن"
     },
     {
         "GlobalLocationNumber": "6240000544003",
         "BPName": "شركة بوعشرين لصناعة الحلويات"
     },
     {
         "GlobalLocationNumber": "6240000545000",
         "BPName": "شركة ديسان لتحلية وتعبئة المياه المعدنية"
     },
     {
         "GlobalLocationNumber": "6241000650008",
         "BPName": "شركة جودة لتعبئة وتغليف المواد الغذائية والبقوليات والمكسرات"
     },
     {
         "GlobalLocationNumber": "6240000546007",
         "BPName": "شركة العاصمة لتعبئة المياة و المشروبات"
     },
     {
         "GlobalLocationNumber": "6240000547004",
         "BPName": "شركة الرسيل لصناعة وتنقية وتعبئة المياه والمشروبات والعصائر"
     },
     {
         "GlobalLocationNumber": "6240000548001",
         "BPName": "مصنع الوادي لتعبئة المياه"
     },
     {
         "GlobalLocationNumber": "6241000660007",
         "BPName": "شركة الموسم لطحن الغلال المساهمة"
     },
     {
         "GlobalLocationNumber": "6240000549008",
         "BPName": "مصنع الانهار الصافية لتنقية وتعبئة المياه"
     },
     {
         "GlobalLocationNumber": "6240000550004",
         "BPName": "مصنع اللبأ لصناعة الألبان ومشتقاته"
     },
     {
         "GlobalLocationNumber": "6240000551001",
         "BPName": "مصنع التقدم لصناعة الصابون ومواد التنظيف"
     },
     {
         "GlobalLocationNumber": "6240000552008",
         "BPName": "شركة غرندل لصناعة المناديل والاكواب البلاستيكية"
     },
     {
         "GlobalLocationNumber": "6240000553005",
         "BPName": "شركة إكليل الجبل للعطرية والزيوت الطبيعية"
     },
     {
         "GlobalLocationNumber": "6240000554002",
         "BPName": "مطحن الاجواد لبيع البقوليات والمكسرات"
     },
     {
         "GlobalLocationNumber": "6240000555009",
         "BPName": "مصنع الفراشة لصناعة الاكياس البلاستيكية"
     },
     {
         "GlobalLocationNumber": "6240000556006",
         "BPName": "شركة البيضاء للصناعات الغذائية"
     },
     {
         "GlobalLocationNumber": "6240000557003",
         "BPName": "شركة الجبل لصناعة وتعبئة المياه"
     },
     {
         "GlobalLocationNumber": "6240000558000",
         "BPName": "شركة النخلة الذهبية لاستيراد المواد الغذائية"
     },
     {
         "GlobalLocationNumber": "6240000559007",
         "BPName": "مصنع الامان لتعبئة المياه"
     },
     {
         "GlobalLocationNumber": "6240000560003",
         "BPName": "محلات الجزيرة لتنقية مياة الشرب"
     },
     {
         "GlobalLocationNumber": "6240000561000",
         "BPName": "شركة مشرق ليبيا لصناعة وتكرير السكر"
     },
     {
         "GlobalLocationNumber": "6241000670006",
         "BPName": "شركة قبس المدينة لاستيراد المواد الغذائية"
     },
     {
         "GlobalLocationNumber": "6240000562007",
         "BPName": "الشركة الأفريقية لتصدير وإستيراد المواد الغذائية 2"
     },
     {
         "GlobalLocationNumber": "6240000563004",
         "BPName": "شركة اندره لتصنيع واستيراد مواد التنظيف"
     },
     {
         "GlobalLocationNumber": "6240000564001",
         "BPName": "شركة أنفاس الفجر للصناعات الغذائية"
     },
     {
         "GlobalLocationNumber": "6240000565008",
         "BPName": "شركة الشهد لتعبئة المياه والمشروبات"
     },
     {
         "GlobalLocationNumber": "6240000566005",
         "BPName": "شركة سبل لصناعة وتعبئة المواد الغذائية والمشروبات والمياه"
     },
     {
         "GlobalLocationNumber": "6241000750005",
         "BPName": "شركة النورين لصناعة المواد الغذائية"
     },
     {
         "GlobalLocationNumber": "6240000567002",
         "BPName": "شركة هيل للصناعات الكيمائية"
     },
     {
         "GlobalLocationNumber": "6240000568009",
         "BPName": "شركة السنبلتين لإستيراد المواد الغذائية"
     },
     {
         "GlobalLocationNumber": "6240000569006",
         "BPName": "شركة الحديقة لصناعة مواد التنظيف"
     },
     {
         "GlobalLocationNumber": "6240000570002",
         "BPName": "شركة أمواج العطاء للصناعات الغذائية"
     },
     {
         "GlobalLocationNumber": "6240000571009",
         "BPName": "شركة نسمة الحياة لتنقية المياه والعصائر والمشروبات"
     },
     {
         "GlobalLocationNumber": "6240000572006",
         "BPName": "شركة الوردة الجميلة لصناعة المناديل الورقية"
     },
     {
         "GlobalLocationNumber": "6240000573003",
         "BPName": "شركة اغلان لتعبيئة المياه والمشروبات"
     },
     {
         "GlobalLocationNumber": "6240000574000",
         "BPName": "تشاركية زهرة النرجس لصناعة الورق الناعم"
     },
     {
         "GlobalLocationNumber": "6240000575007",
         "BPName": "شركة اليعقوبي للقهوة"
     },
     {
         "GlobalLocationNumber": "6240000576004",
         "BPName": "شركة زاد الكرم لاستيراد المواد الغذائية"
     },
     {
         "GlobalLocationNumber": "6240000577001",
         "BPName": "مصنع السنابل المطلة علي المتوسط"
     },
     {
         "GlobalLocationNumber": "6240000578008",
         "BPName": "شركة الرياضي للصناعات الغذائية"
     },
     {
         "GlobalLocationNumber": "6240000579005",
         "BPName": "شركة الدافنية لصناعة المواد الغذائية ومضارب الأرز"
     },
     {
         "GlobalLocationNumber": "6240000580001",
         "BPName": "مصنع تسنيم لتعبئة المياه والمشروبات"
     },
     {
         "GlobalLocationNumber": "6240000581008",
         "BPName": "شركة الربيع لخدمات النظافة"
     },
     {
         "GlobalLocationNumber": "6240000582005",
         "BPName": "شركة رهف للصناعات الغذائية المحدودة"
     },
     {
         "GlobalLocationNumber": "6240000583002",
         "BPName": "شركة باب اليسر لتعبئة المياه"
     },
     {
         "GlobalLocationNumber": "6240000584009",
         "BPName": "شركة العيون الصافية لتعبئة المياه"
     },
     {
         "GlobalLocationNumber": "6240000585006",
         "BPName": "شركة الشرارة الذهبية للخدمات النفطية المساهمة"
     },
     {
         "GlobalLocationNumber": "6240000586003",
         "BPName": "شركة زهرة الصحة لتعبئة المياه والمشروبات الغازية"
     },
     {
         "GlobalLocationNumber": "6240000587000",
         "BPName": "شركة الجادول لصناعة المواد الغذائية والمشروبات"
     },
     {
         "GlobalLocationNumber": "6240000589004",
         "BPName": "مصنع عادل زيتون للحلويات"
     },
     {
         "GlobalLocationNumber": "6240000590000",
         "BPName": "شركة المتميز للصناعات الغذائية"
     },
     {
         "GlobalLocationNumber": "6240000591007",
         "BPName": "شركة الاوركيدة العالمية لتعبئة وتغليف مياه الشرب والمشروبات ذات المسؤولية ا"
     },
     {
         "GlobalLocationNumber": "6240000592004",
         "BPName": "مصنع الطبيعة لصناعة الألبان ومشتقاتها"
     },
     {
         "GlobalLocationNumber": "6240000593001",
         "BPName": "شركة التمور الافريقية لاستيراد المواد الغذائية"
     },
     {
         "GlobalLocationNumber": "6240000594008",
         "BPName": "شركة المتفوق الوطني لصناعة الخزانات والمعدات البلاستيكيه ذات مسئولية محدودة"
     },
     {
         "GlobalLocationNumber": "6240000595005",
         "BPName": "شركة تمرونانة للصناعات الغذائية"
     },
     {
         "GlobalLocationNumber": "6240000596002",
         "BPName": "شركة النبأ المحدودة لتحلية المياه"
     },
     {
         "GlobalLocationNumber": "6240000597009",
         "BPName": "شركة نجمة اويا لصناعة الحفاظات"
     },
     {
         "GlobalLocationNumber": "6240000598006",
         "BPName": "شركة القطرة لتعبئة المياه والمشروبات"
     },
     {
         "GlobalLocationNumber": "6241000680005",
         "BPName": "شركة الخليج الزاهر لصناعة المواد الغذائية 2"
     },
     {
         "GlobalLocationNumber": "6240000599003",
         "BPName": "شركة المزرعة للمطاحن والأعلاف المساهمة"
     },
     {
         "GlobalLocationNumber": "6240000600006",
         "BPName": "شركة رقية لصناعة وتعبئة المياه والعصائر"
     },
     {
         "GlobalLocationNumber": "6241000690004",
         "BPName": "شركة الطيب لاستيراد المواد الغذائية"
     },
     {
         "GlobalLocationNumber": "6240000601003",
         "BPName": "شركة زاد الخير لضرب الارز"
     },
     {
         "GlobalLocationNumber": "6240000602000",
         "BPName": "شركة يشفين المتألقة لتعبئة المياه والمشروبات"
     },
     {
         "GlobalLocationNumber": "6240000604004",
         "BPName": "شركة نور الغد للصناعات الغذائية"
     },
     {
         "GlobalLocationNumber": "6241000700000",
         "BPName": "مطاحن التونسي لصناعة الحبوب والتوابل والبن"
     },
     {
         "GlobalLocationNumber": "6240000605001",
         "BPName": "شركة الدار البيضاء للصناعات الغذائية وتعبئة المياه"
     },
     {
         "GlobalLocationNumber": "6240000607005",
         "BPName": "شركة المحيط لتعبئة المياه والمشروبات"
     },
     {
         "GlobalLocationNumber": "6240000608002",
         "BPName": "شركة مسافي لتعبئة المياه والمشروبات الغازية"
     },
     {
         "GlobalLocationNumber": "6240000609009",
         "BPName": "مصنع موفى لتعبئة المياه المعدنية"
     },
     {
         "GlobalLocationNumber": "6240000610005",
         "BPName": "مطحن بالخير لصناعة القهوة"
     },
     {
         "GlobalLocationNumber": "6240000611002",
         "BPName": "شركة سوق الوسيط لخدمات التسوق"
     },
     {
         "GlobalLocationNumber": "6240000612009",
         "BPName": "مطحن جهاد لصناعة القهوة"
     },
     {
         "GlobalLocationNumber": "6240000613006",
         "BPName": "شركة التمور الذهبية لبيع وتوزيع التمور"
     },
     {
         "GlobalLocationNumber": "6240000614003",
         "BPName": "شركة الاستثمارية للمطاحن والاعلاف المحدودة"
     },
     {
         "GlobalLocationNumber": "6241000710009",
         "BPName": "شركة دار الوفاء لبيع وتوزيع المواد الغذائية"
     },
     {
         "GlobalLocationNumber": "6240000615000",
         "BPName": "شركة دافق للصناعات الغذائية"
     },
     {
         "GlobalLocationNumber": "6240000616007",
         "BPName": "شركة تمكين لاستراد المواد الغذائية المحدودة"
     },
     {
         "GlobalLocationNumber": "6240000617004",
         "BPName": "شركة النظيف لصناعة الصابون ومواد التنظيف"
     },
     {
         "GlobalLocationNumber": "6240000618001",
         "BPName": "شركة الليثي لاستيراد المواد الغذائية"
     },
     {
         "GlobalLocationNumber": "6240000619008",
         "BPName": "مطحن باله 2"
     },
     {
         "GlobalLocationNumber": "6240000620004",
         "BPName": "شركة الطائر الذهبي لاستيراد المواد الغذائية"
     },
     {
         "GlobalLocationNumber": "6240000621001",
         "BPName": "مخبز خيرات ليبيا"
     },
     {
         "GlobalLocationNumber": "6241000720008",
         "BPName": "شركة الاريل للصناعات الغذائية"
     },
     {
         "GlobalLocationNumber": "6240000622008",
         "BPName": "مطحن اللوتس للبن و المكسرات"
     },
     {
         "GlobalLocationNumber": "6240000623005",
         "BPName": "شركة الطلع النضيد للتمور"
     },
     {
         "GlobalLocationNumber": "6241000730007",
         "BPName": "شركة المسار الاولل لاستيراد المواد الغذائية"
     },
     {
         "GlobalLocationNumber": "6241000740006",
         "BPName": "شركة مجموعة المساندة الحديثة"
     },
     {
         "GlobalLocationNumber": "6241000760004",
         "BPName": "شركة اساور الخير"
     },
     {
         "GlobalLocationNumber": "6241000770003",
         "BPName": "شركة مجموعة العلامة الذهبية"
     },
     {
         "GlobalLocationNumber": "6240000624002",
         "BPName": "شركة المراعي الخصبة المحدودة"
     },
     {
         "GlobalLocationNumber": "6240000625009",
         "BPName": "شركة جبل المسيد ذ م م"
     },
     {
         "GlobalLocationNumber": "6240000626006",
         "BPName": "شركة راما لصناعة المواد الغذائية"
     },
     {
         "GlobalLocationNumber": "6240000627003",
         "BPName": "شركة القمودي وشركاؤه ذات توصية بسيطة"
     },
     {
         "GlobalLocationNumber": "6240000628000",
         "BPName": "مصنع رواسي لصناعة الحلويات"
     },
     {
         "GlobalLocationNumber": "6240000630003",
         "BPName": "شركة بيور لتعبئة المياه والعصائر"
     },
     {
         "GlobalLocationNumber": "6240000631000",
         "BPName": "شركة سنابل الجنوب للصناعات الغذائية المساهمة"
     },
     {
         "GlobalLocationNumber": "6240000632007",
         "BPName": "شركة المتكاملة العالمية"
     },
     {
         "GlobalLocationNumber": "6241000780002",
         "BPName": "شركة اللؤلؤة لإستيراد المواد الغدائية ذات المسؤولية المحدودة"
     },
     {
         "GlobalLocationNumber": "6240000633004",
         "BPName": "شركة السنبلة الجديدة لمطاحن الدقيق ومضارب الأرز ومشتقاتها"
     },
     {
         "GlobalLocationNumber": "6240000634001",
         "BPName": "شركة الثلج لتعبئة وتوزيع المياه"
     },
     {
         "GlobalLocationNumber": "6240000635008",
         "BPName": "شركة الكنوز لصناعة المواد الغذائية"
     },
     {
         "GlobalLocationNumber": "6240000636005",
         "BPName": "شركة النجم الذهبي لاستيراد وتصدير منسوجات والمصنوعات الجلدية المساهمة"
     },
     {
         "GlobalLocationNumber": "6241000790001",
         "BPName": "شركة الرائدة لصناعة مواد التنظيف ذات المسؤلية المحدودة"
     },
     {
         "GlobalLocationNumber": "6240000637002",
         "BPName": "شركة الزهرة الليبية للصناعات الغذائية"
     },
     {
         "GlobalLocationNumber": "6240000638009",
         "BPName": "فرع شركة برنتشي للتعهدات والتموين ذات المسوؤلية المحدودة"
     },
     {
         "GlobalLocationNumber": "6240000639006",
         "BPName": "شركة الحديثة المتميزة لطحن البن والحبوب ذ.م.م"
     },
     {
         "GlobalLocationNumber": "6241000800007",
         "BPName": "شركة الدالي للصناعات الغذائية ذ.م.م"
     },
     {
         "GlobalLocationNumber": "6241000810006",
         "BPName": "شركة الجوف لتعبئة المياه والمشروبات الغازية"
     },
     {
         "GlobalLocationNumber": "6240000640002",
         "BPName": "شركة الطاحونة الحمراء لصناعة الحلويات"
     },
     {
         "GlobalLocationNumber": "6240000641009",
         "BPName": "شركة النخلة الذهبية للخدمات الزراعية"
     },
     {
         "GlobalLocationNumber": "6240000642006",
         "BPName": "شركة جنة لتعبئة المياه"
     },
     {
         "GlobalLocationNumber": "6240000643003",
         "BPName": "شركة صح لصناعة مناديل الورق الناعمة"
     },
     {
         "GlobalLocationNumber": "6240000644000",
         "BPName": "شركة النوى لتعبئة وتغليف التمور"
     },
     {
         "GlobalLocationNumber": "6240000645007",
         "BPName": "شركة كوكو لصناعة رقائق الالمونيوم والاكواب الورقية"
     },
     {
         "GlobalLocationNumber": "6241000820005",
         "BPName": "شركة إكليل الجبل لصناعات الغذائية"
     },
     {
         "GlobalLocationNumber": "6241000830004",
         "BPName": "شركة الميار الدولية لاستيراد المواد الغذائية"
     },
     {
         "GlobalLocationNumber": "6241000840003",
         "BPName": "شركة سما افريقا لاستيراد المواد الغذائية"
     },
     {
         "GlobalLocationNumber": "6241000850002",
         "BPName": "شركة الفراس للصناعات الغذائية"
     },
     {
         "GlobalLocationNumber": "6240000646004",
         "BPName": "شركة البركة لتوزيع الاكياس ومواد التنظيف والعطور"
     },
     {
         "GlobalLocationNumber": "6240000647001",
         "BPName": "شركة العائلة للصناعات الغذائية"
     },
     {
         "GlobalLocationNumber": "6240000648008",
         "BPName": "شركة أكوا ليبيا لتعبئة المياة"
     },
     {
         "GlobalLocationNumber": "6241000860001",
         "BPName": "شركة القبطان لصناعة مواد التعبئة والتغليف الغذائي"
     },
     {
         "GlobalLocationNumber": "6240000649005",
         "BPName": "شركة البيلسان لتعبئة وتغليف وتوزيع المواد الغذائية والبن والتوابل ذات المسؤلية المحدودة"
     },
     {
         "GlobalLocationNumber": "6240000650001",
         "BPName": "شركة السهم الذهبي ش م م"
     },
     {
         "GlobalLocationNumber": "6240000651008",
         "BPName": "مطحن تهامة للبن والمكسرات"
     },
     {
         "GlobalLocationNumber": "6240000652005",
         "BPName": "شركة مجموعة الشمال للصناعات الغذائية"
     },
     {
         "GlobalLocationNumber": "6240000653002",
         "BPName": "شركة اللوتس الجديد لصناعة الصابون ومواد التنظيف"
     },
     {
         "GlobalLocationNumber": "6240000654009",
         "BPName": "شركة مائدة بلادي لتغليف وتعبئة وتوزيع المواد الغذائية"
     },
     {
         "GlobalLocationNumber": "6240000655006",
         "BPName": "شركة أسيل الدولية للصناعات الغذائية"
     },
     {
         "GlobalLocationNumber": "6241000260009",
         "BPName": "شركة االنخلتين لإستيراد الواد الغذائية 2"
     },
     {
         "GlobalLocationNumber": "6240000656003",
         "BPName": "شركة هتون لاستيراد المواد الغذائية"
     },
     {
         "GlobalLocationNumber": "6240000657000",
         "BPName": "شركة امداد لصناعة المواد الغذائية"
     },
     {
         "GlobalLocationNumber": "6240000658007",
         "BPName": "مطحن طيبة للقهوة"
     },
     {
         "GlobalLocationNumber": "6241000870000",
         "BPName": "شركة الزاوية الغربية للصناعات الغذائية"
     },
     {
         "GlobalLocationNumber": "6240000659004",
         "BPName": "شركة المراعي الدولية للصناعات الغذائية"
     },
     {
         "GlobalLocationNumber": "6240000660000",
         "BPName": "مطحن الشريف للقهوة"
     },
     {
         "GlobalLocationNumber": "6240000661007",
         "BPName": "شركة الهروج لصناعة المواد الغذائية والمشروبات المساهمة"
     },
     {
         "GlobalLocationNumber": "6240000662004",
         "BPName": "شركة الباقة للخدمات التموينية"
     },
     {
         "GlobalLocationNumber": "6241000880009",
         "BPName": "مصنع التفوق لصناعة وتحميص وتعبئة المواد الغذائية"
     },
     {
         "GlobalLocationNumber": "6241000890008",
         "BPName": "شركة الصدارة لصناعة وتعبئة وتغليف وتجهيز المواد الغذائة والبقوليات"
     },
     {
         "GlobalLocationNumber": "6240000663001",
         "BPName": "شركة جهود للصناعات الغذائية المساهمة"
     },
     {
         "GlobalLocationNumber": "6240000664008",
         "BPName": "شركة المواني لاستيراد المواد الغذائية"
     },
     {
         "GlobalLocationNumber": "6241000900004",
         "BPName": "شركة كرم الضيافة للصناعات الغذائية والحلويات ذات المسؤولية المحدودة"
     },
     {
         "GlobalLocationNumber": "6240000665005",
         "BPName": "شركة المروة الاولى للصناعات الغذائية ذات المسؤلية المحدودة"
     },
     {
         "GlobalLocationNumber": "6241000910003",
         "BPName": "شركة الجيد لاستيراد الملابس والمواد الغذائية والاثاث والقرطاسية"
     },
     {
         "GlobalLocationNumber": "6240000666002",
         "BPName": "شركة اجواد بدر للخدمات التموينية"
     },
     {
         "GlobalLocationNumber": "6240000667009",
         "BPName": "شركة ساسو لانتاج العسل والخلطات الطبيعية"
     },
     {
         "GlobalLocationNumber": "6240000668006",
         "BPName": "شركة شعاع لتعبئة وتغليف المواد الغذائية ذ.م.م"
     },
     {
         "GlobalLocationNumber": "6241000920002",
         "BPName": "شركة راكان المتوسط لاستيراد المواد الغذائية"
     },
     {
         "GlobalLocationNumber": "6241000930001",
         "BPName": "شركة نسمة الحديثة للصناعات الغذائية"
     },
     {
         "GlobalLocationNumber": "6240000669003",
         "BPName": "السلوى للصناعات الغذائية وتنقية ومعالجة المياة"
     },
     {
         "GlobalLocationNumber": "6241000940000",
         "BPName": "شركة هفا لتعبئة المياة المحدودة"
     },
     {
         "GlobalLocationNumber": "6241000950009",
         "BPName": "شركة الريادة التجارية لاستيراد المواد الغذائية ومواد التنظيف والزينة والخردوات"
     },
     {
         "GlobalLocationNumber": "6240000670009",
         "BPName": "شركة الزهرات لصناعة الالبان ومشتقتها المساهمة"
     },
     {
         "GlobalLocationNumber": "6241000960008",
         "BPName": "شركة العاصمة للبن والمكسرات ذ.م.م"
     },
     {
         "GlobalLocationNumber": "6241000970007",
         "BPName": "شركة الراكان لاستيراد الملابس والاثاث والقرطاسية والمواد الغذائية"
     },
     {
         "GlobalLocationNumber": "6242000100005",
         "BPName": "شركة طيب الانفاس لصناعة وخلط الروائح والعطور المحدودة"
     },
     {
         "GlobalLocationNumber": "6241000980006",
         "BPName": "الغيران لتحلية وتعبئة المياه"
     },
     {
         "GlobalLocationNumber": "6241001020008",
         "BPName": "شركة النافورة لتقنية وتعبئة مياة الشرب والعصائر"
     },
     {
         "GlobalLocationNumber": "6241001030007",
         "BPName": "شركة الفتيل لصناعة مواد التنظيف"
     },
     {
         "GlobalLocationNumber": "6241000990005",
         "BPName": "شركة أصل اليمن لتحميص البن و التوابل والمكسرات"
     },
     {
         "GlobalLocationNumber": "6241001010009",
         "BPName": "شركة نسيم الصباح لصناعة مواد الصابون ومواد التنظيف"
     },
     {
         "GlobalLocationNumber": "6241001040006",
         "BPName": "شركة الفضيل لتصنيع المشروبات الغازية والعصائر ومشتقاتها"
     },
     {
         "GlobalLocationNumber": "6241001050005",
         "BPName": "شركة الطمزيني لاستيراد المواد الغذائية ذات التوصية البسيطة"
     },
     {
         "GlobalLocationNumber": "6241001060004",
         "BPName": "شركة الشاهين لصناعة وتعبئة وتغليف المواد الغذائية"
     },
     {
         "GlobalLocationNumber": "6241001070003",
         "BPName": "شركة الرسالة لاستيراد المواد الغذائية"
     },
     {
         "GlobalLocationNumber": "6241001080002",
         "BPName": "شركة اصيلة للصناعات الغذائية وتعبئة المشروبات"
     },
     {
         "GlobalLocationNumber": "6241001090001",
         "BPName": "شركة اللؤلؤة لتعبئة وتغليف المواد الغذائية"
     },
     {
         "GlobalLocationNumber": "6241001100007",
         "BPName": "شركة الاستدامة للصناعات الغذائية ذات المسؤولية المحدودة"
     },
     {
         "GlobalLocationNumber": "6240000671006",
         "BPName": "شركة ادران لاستيراد المواد الغذائية"
     },
     {
         "GlobalLocationNumber": "6241001110006",
         "BPName": "شركة مارة لتصنيع مياه الشرب والمشروبات ذات المسؤولية المحدودة"
     },
     {
         "GlobalLocationNumber": "6241001120005",
         "BPName": "شركة الاصالة الذهبية لمطاحن الدقيق ومضارب الارز"
     },
     {
         "GlobalLocationNumber": "6241001130004",
         "BPName": "شركة الشعلة للصناعات الغذائية"
     },
     {
         "GlobalLocationNumber": "6241001140003",
         "BPName": "شركة فريش لاستيراد المواد الغذائية و المواشي واللحوم والملابس والاثاث والكتب والقرطاسية"
     },
     {
         "GlobalLocationNumber": "6241001150002",
         "BPName": "شركة أصيل لتعبئة وتنقية مياة الشرب والعصائر"
     },
     {
         "GlobalLocationNumber": "6241001160001",
         "BPName": "شركة سهل بنغازي المساهمة لطحن الحبوب وصناعة الدقيق"
     },
     {
         "GlobalLocationNumber": "6241001170000",
         "BPName": "شركة الخيرات الباهرة لتسويق وتعبئة وتغليف المواد الغذائية"
     },
     {
         "GlobalLocationNumber": "6241001180009",
         "BPName": "شركة الكاملة الاقتصادية لاستيراد المواد الغذائية ومواد التنظيف والاثاث والقرطاسية"
     },
     {
         "GlobalLocationNumber": "6241001190008",
         "BPName": "شركة مروج البادية للصناعات الغذائية المساهمة"
     },
     {
         "GlobalLocationNumber": "6241001200004",
         "BPName": "شركة المستقبل الراقي لاستيراد المواد الغذائية المحدودة"
     },
     {
         "GlobalLocationNumber": "6241001210003",
         "BPName": "شركة هجين للتوريدات والتجهيز ذ.م.م"
     },
     {
         "GlobalLocationNumber": "6241001220002",
         "BPName": "شركة الياسمين لصناعة الخبيز"
     },
     {
         "GlobalLocationNumber": "6241001230001",
         "BPName": "محل الشهية لذبح و تنظيف و تفريغ الدواجن"
     },
     {
         "GlobalLocationNumber": "6241001240000",
         "BPName": "شركة عالم النكهات لاستيراد المواد الغذائية والفواكه والخضروات واللحوم"
     },
     {
         "GlobalLocationNumber": "6241001250009",
         "BPName": "شركة هنا لصناعة المناديل الورقية والفوط الصحية ذ.م.م"
     }
 ]